{\"0\": [{ \"xAxis\": \"0\", \"yAxis\":42.6226660904263},{ \"xAxis\": \"1\", \"yAxis\":57.3773339095737},{\"childrenIndex\":[1, 2, 3, 4, 5, 6, 7, 8, 9, 10, 11, 12, 13, 14], \"populationSize\":448481122585, \"filter\":\"#\",\"yName\":\"slots_millis_reduces\"}],\"3\": [{ \"xAxis\": \"0\", \"yAxis\":99.07895910376558},{ \"xAxis\": \"1\", \"yAxis\":0.9210408962344133},{\"childrenIndex\":[15, 17, 39, 41, 42, 45, 46, 49, 50, 53, 54], \"populationSize\":56725332082, \"filter\":\"#is_profile_query$0#\",\"yName\":\"slots_millis_reduces\"}],\"6\": [{ \"xAxis\": \"0\", \"yAxis\":99.07895910376558},{ \"xAxis\": \"1\", \"yAxis\":0.9210408962344133},{\"childrenIndex\":[20, 22, 39, 59, 60, 63, 64, 67, 68, 71, 72], \"populationSize\":56725332082, \"filter\":\"#is_event_query$1#\",\"yName\":\"slots_millis_reduces\"}],\"8\": [{ \"xAxis\": \"0\", \"yAxis\":98.69961173952065},{ \"xAxis\": \"1\", \"yAxis\":1.3003882604793606},{\"childrenIndex\":[24, 26, 42, 60, 75, 76, 79, 80, 83], \"populationSize\":48034401108, \"filter\":\"#has_impressions_tbl$1#\",\"yName\":\"slots_millis_reduces\"}],\"12\": [{ \"xAxis\": \"0\", \"yAxis\":97.29957989744665},{ \"xAxis\": \"1\", \"yAxis\":2.700420102553362},{\"childrenIndex\":[32, 34, 86, 88, 95], \"populationSize\":35621903462, \"filter\":\"#has_actions_tbl$1#\",\"yName\":\"slots_millis_reduces\"}],\"10\": [{ \"xAxis\": \"0\", \"yAxis\":96.452847314117},{ \"xAxis\": \"1\", \"yAxis\":3.5471526858830025},{\"childrenIndex\":[28, 30, 87, 88, 91], \"populationSize\":41251572982, \"filter\":\"#has_clicks_tbl$1#\",\"yName\":\"slots_millis_reduces\"}],\"13\": [{ \"xAxis\": \"0\", \"yAxis\":87.94379871435501},{ \"xAxis\": \"1\", \"yAxis\":12.056201285644988},{\"childrenIndex\":[35, 37, 55, 69, 81, 89, 93], \"populationSize\":100662793441, \"filter\":\"#has_distinct$0#\",\"yName\":\"slots_millis_reduces\"}],\"86\": [{ \"xAxis\": \"0\", \"yAxis\":74.2299700357223},{ \"xAxis\": \"1\", \"yAxis\":25.7700299642777},{\"childrenIndex\":[190, 194], \"populationSize\":1667725166, \"filter\":\"#has_clicks_tbl$0#has_actions_tbl$1#\",\"yName\":\"slots_millis_reduces\"}],\"54\": [{ \"xAxis\": \"0\", \"yAxis\":84.27088592272341},{ \"xAxis\": \"1\", \"yAxis\":15.729114077276583},{\"childrenIndex\":[126, 226, 246, 262, 270], \"populationSize\":2413842408, \"filter\":\"#is_profile_query$0#has_distinct$1#\",\"yName\":\"slots_millis_reduces\"}],\"72\": [{ \"xAxis\": \"0\", \"yAxis\":84.27088592272341},{ \"xAxis\": \"1\", \"yAxis\":15.729114077276583},{\"childrenIndex\":[160, 226, 298, 314, 322], \"populationSize\":2413842408, \"filter\":\"#is_event_query$1#has_distinct$1#\",\"yName\":\"slots_millis_reduces\"}],\"55\": [{ \"xAxis\": \"0\", \"yAxis\":74.12516900001701},{ \"xAxis\": \"1\", \"yAxis\":25.87483099998299},{\"childrenIndex\":[127, 227, 249, 265, 267, 273, 275], \"populationSize\":46351303767, \"filter\":\"#is_profile_query$1#has_distinct$0#\",\"yName\":\"slots_millis_reduces\"}],\"275\": [{ \"xAxis\": \"0\", \"yAxis\":27.315651301387227},{ \"xAxis\": \"1\", \"yAxis\":72.68434869861278},{\"childrenIndex\":[482, 689, 732], \"populationSize\":39850322, \"filter\":\"#is_profile_query$1#has_actions_tbl$1#has_distinct$0#\",\"yName\":\"slots_millis_reduces\"}],\"482\": [{ \"xAxis\": \"0\", \"yAxis\":13.43071232890878},{ \"xAxis\": \"1\", \"yAxis\":86.56928767109122},{\"childrenIndex\":[924], \"populationSize\":33458687, \"filter\":\"#is_multi_query$1#is_profile_query$1#has_actions_tbl$1#has_distinct$0#\",\"yName\":\"slots_millis_reduces\"}],\"69\": [{ \"xAxis\": \"0\", \"yAxis\":74.12516900001701},{ \"xAxis\": \"1\", \"yAxis\":25.87483099998299},{\"childrenIndex\":[157, 227, 293, 309, 311, 317, 319], \"populationSize\":46351303767, \"filter\":\"#is_event_query$0#has_distinct$0#\",\"yName\":\"slots_millis_reduces\"}],\"319\": [{ \"xAxis\": \"0\", \"yAxis\":27.315651301387227},{ \"xAxis\": \"1\", \"yAxis\":72.68434869861278},{\"childrenIndex\":[573, 689, 786], \"populationSize\":39850322, \"filter\":\"#is_event_query$0#has_actions_tbl$1#has_distinct$0#\",\"yName\":\"slots_millis_reduces\"}],\"573\": [{ \"xAxis\": \"0\", \"yAxis\":13.43071232890878},{ \"xAxis\": \"1\", \"yAxis\":86.56928767109122},{\"childrenIndex\":[924], \"populationSize\":33458687, \"filter\":\"#is_multi_query$1#is_event_query$0#has_actions_tbl$1#has_distinct$0#\",\"yName\":\"slots_millis_reduces\"}],\"2\": [{ \"xAxis\": \"0\", \"yAxis\":29.169135839330806},{ \"xAxis\": \"1\", \"yAxis\":70.8308641606692},{\"childrenIndex\":[18, 21, 25, 29, 33, 38], \"populationSize\":75423088823, \"filter\":\"#is_multi_query$1#\",\"yName\":\"slots_millis_reduces\"}],\"14\": [{ \"xAxis\": \"0\", \"yAxis\":29.506187085244463},{ \"xAxis\": \"1\", \"yAxis\":70.49381291475554},{\"childrenIndex\":[36, 38, 56, 70, 82, 84, 90, 92, 94, 96], \"populationSize\":347818329144, \"filter\":\"#has_distinct$1#\",\"yName\":\"slots_millis_reduces\"}],\"92\": [{ \"xAxis\": \"0\", \"yAxis\":4.967143405001682},{ \"xAxis\": \"1\", \"yAxis\":95.03285659499832},{\"childrenIndex\":[200, 204, 336, 340, 354], \"populationSize\":1478600415, \"filter\":\"#has_clicks_tbl$1#has_distinct$1#\",\"yName\":\"slots_millis_reduces\"}],\"96\": [{ \"xAxis\": \"0\", \"yAxis\":8.366873216617686},{ \"xAxis\": \"1\", \"yAxis\":91.63312678338231},{\"childrenIndex\":[208, 212, 344, 352, 356], \"populationSize\":1005717821, \"filter\":\"#has_actions_tbl$1#has_distinct$1#\",\"yName\":\"slots_millis_reduces\"}],\"84\": [{ \"xAxis\": \"0\", \"yAxis\":14.655460009094304},{ \"xAxis\": \"1\", \"yAxis\":85.3445399909057},{\"childrenIndex\":[184, 340, 346], \"populationSize\":621479148, \"filter\":\"#has_impressions_tbl$1#has_distinct$1#\",\"yName\":\"slots_millis_reduces\"}],\"346\": [{ \"xAxis\": \"0\", \"yAxis\":2.1648915084750877},{ \"xAxis\": \"1\", \"yAxis\":97.83510849152492},{\"childrenIndex\":[616, 828], \"populationSize\":542135158, \"filter\":\"#has_impressions_tbl$1#has_actions_tbl$0#has_distinct$1#\",\"yName\":\"slots_millis_reduces\"}],\"81\": [{ \"xAxis\": \"0\", \"yAxis\":77.38609790204538},{ \"xAxis\": \"1\", \"yAxis\":22.613902097954625},{\"childrenIndex\":[181, 185, 333, 335, 341, 343], \"populationSize\":53249871481, \"filter\":\"#has_impressions_tbl$0#has_distinct$0#\",\"yName\":\"slots_millis_reduces\"}],\"335\": [{ \"xAxis\": \"0\", \"yAxis\":39.864903379477674},{ \"xAxis\": \"1\", \"yAxis\":60.13509662052232},{\"childrenIndex\":[819, 821], \"populationSize\":79576676, \"filter\":\"#has_impressions_tbl$0#has_clicks_tbl$1#has_distinct$0#\",\"yName\":\"slots_millis_reduces\"}],\"185\": [{ \"xAxis\": \"0\", \"yAxis\":44.16407274131128},{ \"xAxis\": \"1\", \"yAxis\":55.83592725868871},{\"childrenIndex\":[603, 619, 621], \"populationSize\":3664546147, \"filter\":\"#is_multi_query$1#has_impressions_tbl$0#has_distinct$0#\",\"yName\":\"slots_millis_reduces\"}],\"821\": [{ \"xAxis\": \"0\", \"yAxis\":68.51796144483146},{ \"xAxis\": \"1\", \"yAxis\":31.482038555168547},{\"childrenIndex\":[1252, 1264], \"populationSize\":23648710, \"filter\":\"#has_impressions_tbl$0#has_clicks_tbl$1#has_actions_tbl$1#has_distinct$0#\",\"yName\":\"slots_millis_reduces\"}],\"1252\": [{ \"xAxis\": \"0\", \"yAxis\":46.19324463270985},{ \"xAxis\": \"1\", \"yAxis\":53.80675536729015},{\"childrenIndex\":[1493], \"populationSize\":13836731, \"filter\":\"#is_profile_query$1#has_impressions_tbl$0#has_clicks_tbl$1#has_actions_tbl$1#has_distinct$0#\",\"yName\":\"slots_millis_reduces\"}],\"1264\": [{ \"xAxis\": \"0\", \"yAxis\":46.19324463270985},{ \"xAxis\": \"1\", \"yAxis\":53.80675536729015},{\"childrenIndex\":[1493], \"populationSize\":13836731, \"filter\":\"#is_event_query$0#has_impressions_tbl$0#has_clicks_tbl$1#has_actions_tbl$1#has_distinct$0#\",\"yName\":\"slots_millis_reduces\"}],\"343\": [{ \"xAxis\": \"0\", \"yAxis\":91.39887086997128},{ \"xAxis\": \"1\", \"yAxis\":8.601129130028717},{\"childrenIndex\":[817, 821], \"populationSize\":336757495, \"filter\":\"#has_impressions_tbl$0#has_actions_tbl$1#has_distinct$0#\",\"yName\":\"slots_millis_reduces\"}],\"819\": [{ \"xAxis\": \"0\", \"yAxis\":27.74917829123269},{ \"xAxis\": \"1\", \"yAxis\":72.2508217087673},{\"childrenIndex\":[1236, 1274], \"populationSize\":55927966, \"filter\":\"#has_impressions_tbl$0#has_clicks_tbl$1#has_actions_tbl$0#has_distinct$0#\",\"yName\":\"slots_millis_reduces\"}]}